ez_setup.py
setup.py
recaptcha/__init__.py
recaptcha/client/__init__.py
recaptcha/client/captcha.py
recaptcha/client/mailhide.py
recaptcha_client.egg-info/PKG-INFO
recaptcha_client.egg-info/SOURCES.txt
recaptcha_client.egg-info/dependency_links.txt
recaptcha_client.egg-info/namespace_packages.txt
recaptcha_client.egg-info/requires.txt
recaptcha_client.egg-info/top_level.txt
