Metadata-Version: 1.0
Name: recaptcha-client
Version: 1.0.1
Summary: A plugin for reCAPTCHA and reCAPTCHA Mailhide
Home-page: http://recaptcha.net/
Author: Ben Maurer
Author-email: support@recaptcha.net
License: MIT/X11
Platform: UNKNOWN
Classifier: Topic :: Security
Classifier: Topic :: Internet :: WWW/HTTP :: Dynamic Content :: CGI Tools/Libraries
Classifier: Development Status :: 4 - Beta
Classifier: Environment :: Web Environment
